{
  "project_info": {
    "project_number": "1002036007446",
    "project_id": "pay-464a4",
    "storage_bucket": "pay-464a4.appspot.com"
  },
  "client": [
    {
      "client_info": {
        "mobilesdk_app_id": "1:1002036007446:android:9b05a5669c11937b599b37",
        "android_client_info": {
          "package_name": "com.masai.sainath.gpay"
        }
      },
      "oauth_client": [
        {
          "client_id": "1002036007446-70vnl54o5nh5oe9ubl3k9voa9adl49nc.apps.googleusercontent.com",
          "client_type": 3
        }
      ],
      "api_key": [
        {
          "current_key": "AIzaSyCzjtHSTT0gUCG8G3F2ROsUtyC81rV-H8U"
        }
      ],
      "services": {
        "appinvite_service": {
          "other_platform_oauth_client": [
            {
              "client_id": "1002036007446-70vnl54o5nh5oe9ubl3k9voa9adl49nc.apps.googleusercontent.com",
              "client_type": 3
            }
          ]
        }
      }
    }
  ],
  "configuration_version": "1"
}